pysip/__init__.py
pysip/pysip.py
pysip-1.1.0.dist-info/LICENSE
pysip-1.1.0.dist-info/METADATA
pysip-1.1.0.dist-info/WHEEL
pysip-1.1.0.dist-info/top_level.txt
pysip-1.1.0.dist-info/RECORD
