Metadata-Version: 2.1
Name: pysip
Version: 1.1.0
Summary: A thin wrapper around requests to interact with the Simple Intel Platform (SIP).
Home-page: https://github.com/IntegralDefense/pysip
Author: Matthew Wilson
Author-email: automationator@runbox.com
License: Apache 2.0
Keywords: pysip
Platform: UNKNOWN
Classifier: Development Status :: 3 - Alpha
Classifier: Intended Audience :: Developers
Classifier: Topic :: Software Development :: Libraries :: Python Modules
Classifier: License :: OSI Approved :: Apache Software License
Classifier: Programming Language :: Python :: 3
Classifier: Programming Language :: Python :: 3.3
Classifier: Programming Language :: Python :: 3.4
Classifier: Programming Language :: Python :: 3.5
Requires-Dist: requests
